{
    "boxShadow": "none",
    "widgetName": "Text1Copy",
    "dynamicPropertyPathList": [{"key": "fontSize"}],
    "displayName": "Text",
    "iconSVG": "/static/media/icon.97c59b52.svg",
    "topRow": 0,
    "bottomRow": 6,
    "type": "TEXT_WIDGET",
    "hideCard": false,
    "animateLoading": true,
    "dynamicTriggerPathList": [],
    "overflow": "NONE",
    "fontFamily": "System Default",
    "leftColumn": 14,
    "dynamicBindingPathList": [],
    "text": "Issues Created",
    "key": "o57hg9bya7",
    "labelTextSize": "0.875rem",
    "rightColumn": 64,
    "textAlign": "LEFT",
    "dynamicHeight": "FIXED",
    "widgetId": "gbgbhak2zd",
    "isVisible": true,
    "fontStyle": "BOLD",
    "textColor": "#2E3D49",
    "version": 1,
    "parentId": "cncjqcorjf",
    "renderMode": "CANVAS",
    "isLoading": false,
    "borderRadius": "0px",
    "maxDynamicHeight": 9000,
    "fontSize": "1.125rem",
    "minDynamicHeight": 4
}