{
    "widgetName": "Text3",
    "displayName": "Text",
    "iconSVG": "/static/media/icon.97c59b52.svg",
    "searchTags": [
        "typography",
        "paragraph"
    ],
    "topRow": 1,
    "bottomRow": 5,
    "parentRowSpace": 10,
    "type": "TEXT_WIDGET",
    "hideCard": false,
    "animateLoading": true,
    "overflow": "NONE",
    "fontFamily": "{{appsmith.theme.fontFamily.appFont}}",
    "parentColumnSpace": 16,
    "dynamicTriggerPathList": [],
    "leftColumn": 47,
    "dynamicBindingPathList": [
        {"key": "fontFamily"},
        {"key": "borderRadius"}
    ],
    "shouldTruncate": false,
    "truncateButtonColor": "#FFC13D",
    "text": "-",
    "key": "m1z4695uta",
    "isDeprecated": false,
    "rightColumn": 49,
    "textAlign": "CENTER",
    "dynamicHeight": "FIXED",
    "widgetId": "m9sr6thmft",
    "isVisible": true,
    "fontStyle": "",
    "textColor": "#231F20",
    "version": 1,
    "parentId": "sol3e9ldhz",
    "renderMode": "CANVAS",
    "isLoading": false,
    "borderRadius": "{{appsmith.theme.borderRadius.appBorderRadius}}",
    "maxDynamicHeight": 9000,
    "fontSize": "1.875rem",
    "minDynamicHeight": 4
}