{
    "boxShadow": "none",
    "widgetName": "Modal1",
    "isCanvas": true,
    "displayName": "Modal",
    "iconSVG": "/static/media/icon.71fb8986.svg",
    "topRow": 0,
    "bottomRow": 0,
    "parentRowSpace": 1,
    "type": "MODAL_WIDGET",
    "hideCard": false,
    "shouldScrollContents": true,
    "parentColumnSpace": 1,
    "dynamicTriggerPathList": [],
    "leftColumn": 0,
    "dynamicBindingPathList": [{"key": "borderRadius"}],
    "children": [{
        "boxShadow": "none",
        "widgetName": "Canvas1",
        "displayName": "Canvas",
        "topRow": 0,
        "bottomRow": 490,
        "parentRowSpace": 1,
        "type": "CANVAS_WIDGET",
        "canExtend": true,
        "hideCard": true,
        "shouldScrollContents": false,
        "minHeight": 494,
        "parentColumnSpace": 1,
        "leftColumn": 0,
        "isDisabled": false,
        "key": "fxpngvg9z7",
        "labelTextSize": "0.875rem",
        "rightColumn": 0,
        "detachFromLayout": true,
        "widgetId": "2n9ketv319",
        "isVisible": true,
        "version": 1,
        "parentId": "dk957r8ofe",
        "renderMode": "CANVAS",
        "isLoading": false,
        "borderRadius": "0px"
    }],
    "key": "rq40i3jz56",
    "height": 494,
    "labelTextSize": "0.875rem",
    "rightColumn": 0,
    "detachFromLayout": true,
    "dynamicHeight": "FIXED",
    "widgetId": "dk957r8ofe",
    "canOutsideClickClose": true,
    "canEscapeKeyClose": true,
    "version": 2,
    "parentId": "0",
    "renderMode": "CANVAS",
    "isLoading": false,
    "borderRadius": "{{appsmith.theme.borderRadius.appBorderRadius}}",
    "maxDynamicHeight": 9000,
    "width": 456,
    "minDynamicHeight": 4
}