{
    "boxShadow": "none",
    "widgetName": "Text3",
    "dynamicPropertyPathList": [{"key": "backgroundColor"}],
    "displayName": "Text",
    "iconSVG": "/static/media/icon.dbad9587.svg",
    "topRow": 20,
    "bottomRow": 24,
    "parentRowSpace": 10,
    "type": "TEXT_WIDGET",
    "hideCard": false,
    "parentColumnSpace": 6.9375,
    "dynamicTriggerPathList": [],
    "overflow": "NONE",
    "fontFamily": "System Default",
    "leftColumn": 53,
    "dynamicBindingPathList": [{"key": "backgroundColor"}],
    "text": "<div/>",
    "key": "96bh7xhx7l",
    "labelTextSize": "0.875rem",
    "rightColumn": 59,
    "backgroundColor": "{{color_input.text}}",
    "textAlign": "LEFT",
    "dynamicHeight": "FIXED",
    "widgetId": "ltvwiu04aa",
    "isVisible": true,
    "fontStyle": "BOLD",
    "textColor": "#231F20",
    "version": 1,
    "parentId": "2n9ketv319",
    "renderMode": "CANVAS",
    "isLoading": false,
    "borderRadius": "0px",
    "maxDynamicHeight": 9000,
    "fontSize": "0.875rem",
    "minDynamicHeight": 4
}